junghomeapi/__init__.py
junghomeapi/api.py
junghomeapi-0.0.3.dist-info/METADATA
junghomeapi-0.0.3.dist-info/WHEEL
junghomeapi-0.0.3.dist-info/licenses/LICENSE
junghomeapi-0.0.3.dist-info/RECORD
