Metadata-Version: 2.4
Name: junghomeapi
Version: 0.0.3
Summary: A paython api for Junghome
Project-URL: Homepage, https://github.com/Edna-Krabappel/junghomeapi
Project-URL: Issues, https://github.com/Edna-Krabappel/junghomeapi/issues
Author-email: Edna Krabbable <tantenic@gmail.com>
License-File: LICENSE
Classifier: License :: OSI Approved :: MIT License
Classifier: Operating System :: OS Independent
Classifier: Programming Language :: Python :: 3
Requires-Python: >=3.8
